network_interface/__init__.py
network_interface-0.0.3.dist-info/LICENSE
network_interface-0.0.3.dist-info/METADATA
network_interface-0.0.3.dist-info/WHEEL
network_interface-0.0.3.dist-info/top_level.txt
network_interface-0.0.3.dist-info/RECORD
