Metadata-Version: 2.1
Name: network-interface
Version: 0.0.3
Summary: This class is an abstract class to standardize the way of creating a network graph in networkx
Home-page: https://github.com/Samer92/network-interface
Author: Muhammad Samer Sallam
Author-email: samersallam92@gmail.com
License: MIT
Platform: UNKNOWN
Classifier: Programming Language :: Python :: 3
Classifier: License :: OSI Approved :: MIT License
Classifier: Operating System :: OS Independent
Requires-Python: >=3.6
Requires-Dist: pandas
Requires-Dist: networkx
